bootstrap_email/__init__.py
bootstrap_email/base.html
bootstrap_email/bootstrap-email.scss
bootstrap_email/bootstrap-head.scss
bootstrap_email/compiler.py
bootstrap_email/scss/_helpers.scss
bootstrap_email/scss/_reboot_email.scss
bootstrap_email/scss/_reboot_head.scss
bootstrap_email/scss/_variables.scss
bootstrap_email/scss/components/_alert.scss
bootstrap_email/scss/components/_badge.scss
bootstrap_email/scss/components/_button.scss
bootstrap_email/scss/components/_card.scss
bootstrap_email/scss/components/_container.scss
bootstrap_email/scss/components/_grid.scss
bootstrap_email/scss/components/_hr.scss
bootstrap_email/scss/components/_image.scss
bootstrap_email/scss/components/_preview.scss
bootstrap_email/scss/components/_stack.scss
bootstrap_email/scss/components/_table.scss
bootstrap_email/scss/helpers/_functions.scss
bootstrap_email/scss/helpers/_mixins.scss
bootstrap_email/scss/helpers/_selectors_for_utils.scss
bootstrap_email/scss/utilities/_background.scss
bootstrap_email/scss/utilities/_border-radius.scss
bootstrap_email/scss/utilities/_border.scss
bootstrap_email/scss/utilities/_color.scss
bootstrap_email/scss/utilities/_display.scss
bootstrap_email/scss/utilities/_sizing.scss
bootstrap_email/scss/utilities/_spacing.scss
bootstrap_email/scss/utilities/_text-decoration.scss
bootstrap_email/scss/utilities/_typography.scss
bootstrap_email/scss/utilities/_valign.scss
bootstrap_email/scss/variables/_body.scss
bootstrap_email/scss/variables/_borders.scss
bootstrap_email/scss/variables/_buttons.scss
bootstrap_email/scss/variables/_colors.scss
bootstrap_email/scss/variables/_tables.scss
bootstrap_email/scss/variables/_typography.scss
bootstrap_email/scss/variables/_utilities.scss
bootstrap_email/templates/body.html
bootstrap_email/templates/container.html
bootstrap_email/templates/div.html
bootstrap_email/templates/table-left.html
bootstrap_email/templates/table-to-tbody.html
bootstrap_email/templates/table-to-tr.html
bootstrap_email/templates/table.html
bootstrap_email-0.4.0.dist-info/LICENSE
bootstrap_email-0.4.0.dist-info/METADATA
bootstrap_email-0.4.0.dist-info/WHEEL
bootstrap_email-0.4.0.dist-info/top_level.txt
bootstrap_email-0.4.0.dist-info/RECORD
