Metadata-Version: 2.1
Name: bootstrap-email
Version: 0.4.0
Summary: Python port of the bootstrap-email Ruby library - Bootstrap 5+ stylesheet, compiler, and inliner for responsive and consistent emails with the Bootstrap syntax you know and love.
Author: Jeremy Thompson
License: MIT License
Project-URL: Homepage, https://github.com/jhthompson/bootstrap-email
Project-URL: Changelog, https://github.com/jhthompson/bootstrap-email/releases
Project-URL: Issues, https://github.com/jhthompson/bootstrap-email/issues
Project-URL: CI, https://github.com/jhthompson/bootstrap-email/actions
Requires-Python: >=3.9
License-File: LICENSE
Requires-Dist: premailer
Requires-Dist: libsass
Requires-Dist: cssutils
Provides-Extra: lint
Requires-Dist: ruff; extra == "lint"
Provides-Extra: test
Requires-Dist: coverage; extra == "test"
